{"atlas":{"type":"msdf","distanceRange":4,"size":42,"width":256,"height":256,"yOrigin":"bottom"},"metrics":{"emSize":1,"lineHeight":1.071429,"ascender":0.976190,"descender":-0.095238},"glyphs":[{"unicode":59648,"advance":1.000000,"planeBounds":{"left":-0.047619,"bottom":-0.166667,"right":1.047619,"top":0.928571},"atlasBounds":{"left":0.5,"bottom":116.5,"right":45.5,"top":161.5}},{"unicode":59649,"advance":1.166667,"planeBounds":{"left":-0.047619,"bottom":-0.166667,"right":1.214286,"top":0.928571},"atlasBounds":{"left":0.5,"bottom":210.5,"right":52.5,"top":255.5}},{"unicode":59650,"advance":0.880952,"planeBounds":{"left":-0.047619,"bottom":-0.166667,"right":0.928571,"top":0.928571},"atlasBounds":{"left":0.5,"bottom":163.5,"right":40.5,"top":208.5}},{"unicode":59651,"advance":0.857143,"planeBounds":{"left":-0.047619,"bottom":-0.166667,"right":0.904762,"top":0.928571},"atlasBounds":{"left":185.5,"bottom":210.5,"right":224.5,"top":255.5}},{"unicode":59652,"advance":1.047619,"planeBounds":{"left":-0.047619,"bottom":-0.166667,"right":1.095238,"top":0.928571},"atlasBounds":{"left":54.5,"bottom":210.5,"right":101.5,"top":255.5}},{"unicode":59653,"advance":0.833333,"planeBounds":{"left":-0.047619,"bottom":-0.166667,"right":0.880952,"top":0.928571},"atlasBounds":{"left":145.5,"bottom":210.5,"right":183.5,"top":255.5}},{"unicode":59654,"advance":0.880952,"planeBounds":{"left":-0.047619,"bottom":-0.166667,"right":0.928571,"top":0.928571},"atlasBounds":{"left":103.5,"bottom":210.5,"right":143.5,"top":255.5}},{"unicode":59655,"advance":1.000000,"planeBounds":{"left":-0.047619,"bottom":-0.166667,"right":1.047619,"top":0.928571},"atlasBounds":{"left":42.5,"bottom":163.5,"right":87.5,"top":208.5}}],"kerning":[]}